Metadata-Version: 2.1
Name: django-tidy
Version: 0.1
Summary: UNKNOWN
Home-page: https://github.com/rtts/django-tidy
Author: Jaap Joris Vens
Author-email: jj@rtts.eu
License: UNKNOWN
Platform: UNKNOWN
Classifier: Programming Language :: Python :: 3
Classifier: License :: OSI Approved :: GNU Affero General Public License v3 or later (AGPLv3+)
Classifier: Operating System :: OS Independent
Requires-Python: >=3.8
